zermelo/__init__.py
zermelo/client.py
zermelo.py-1.0.1.dist-info/LICENSE
zermelo.py-1.0.1.dist-info/METADATA
zermelo.py-1.0.1.dist-info/WHEEL
zermelo.py-1.0.1.dist-info/top_level.txt
zermelo.py-1.0.1.dist-info/RECORD
