Metadata-Version: 2.1
Name: zermelo.py
Version: 1.0.1
Summary: Zermelo api wrapper library for python.
Home-page: https://github.com/wouter173/zermelo.py
License: MIT
Platform: UNKNOWN
Classifier: Programming Language :: Python :: 3
Classifier: Programming Language :: Python :: 3.7
Classifier: Operating System :: OS Independent
Classifier: License :: OSI Approved :: MIT License
Classifier: Development Status :: 5 - Production/Stable
Requires-Dist: requests (>=2.17.0)
